{"colors":
						{"components": [
								{"id":"0","R":"120", "G" :"127","B" : "127","A":"30"},
								{"id":"1","R":"0", "G" :"100","B" : "0","A":"0"},
								{"id":"2","R":"165", "G" :"0","B" : "254","A":"165"},
								{"id":"3","R": "135", "G" :"2","B" : "191","A":"165"},
								{"id":"4","R": "89", "G" :"0","B" : "105","A":"165"},
								{"id":"5","R": "125", "G" :"0","B" : "176","A":"165"},
								{"id":"6","R": "112", "G" :"0","B" : "164","A":"165"},
								{"id":"7","R": "136", "G" :"0","B" : "217","A":"165"},
								{"id":"8","R": "152", "G" :"0","B" : "217","A":"165"},
								{"id":"9","R": "255", "G" :"106","B" : "0","A":"255"},
								{"id":"10","R": "255", "G" :"149","B" : "0","A":"255"},
								{"id":"11","R": "255", "G" :"150","B" : "0","A":"255"},
								{"id":"12","R": "251", "G" :"177","B" : "0","A":"255"},
								{"id":"13","R": "255", "G" :"197","B" : "8","A":"255"},
								{"id":"14","R": "255", "G" :"199","B" : "0","A":"255"},
								{"id":"15","R": "0", "G" :"0","B" : "0","A":"0"},
								{"id":"16","R": "0", "G" :"0","B" : "0","A":"0"},
								{"id":"17","R": "0", "G" :"0","B" : "0","A":"0"}
								],
						"length":"18"}
}
